loading_sdk/__init__.py
loading_sdk/async_api/__init__.py
loading_sdk/async_api/client.py
loading_sdk/async_api/extractors.py
loading_sdk/settings.py
loading_sdk/sync_api/__init__.py
loading_sdk/sync_api/client.py
loading_sdk/sync_api/extractors.py
tests/__init__.py
tests/test_api.py
python_loading_sdk-0.4.1.dist-info/LICENSE.md
python_loading_sdk-0.4.1.dist-info/WHEEL
python_loading_sdk-0.4.1.dist-info/METADATA
python_loading_sdk-0.4.1.dist-info/RECORD
