Metadata-Version: 2.1
Name: python-loading-sdk
Version: 0.4.1
Summary: Python api wrapper for loading.se
Home-page: https://github.com/hnrkcode/python-loading-sdk
License: MIT
Author: hnrkcode
Author-email: 44243358+hnrkcode@users.noreply.github.com
Requires-Python: >=3.8,<4.0
Classifier: License :: OSI Approved :: MIT License
Classifier: Programming Language :: Python :: 3
Classifier: Programming Language :: Python :: 3.8
Classifier: Programming Language :: Python :: 3.9
Classifier: Programming Language :: Python :: 3.10
Requires-Dist: aiohttp (>=3.8.1,<4.0.0)
Requires-Dist: beautifulsoup4 (>=4.11.1,<5.0.0)
Requires-Dist: requests (>=2.28.1,<3.0.0)
Project-URL: Repository, https://github.com/hnrkcode/python-loading-sdk
